{"edge": {"All-Purpose Flour": {"Basic Pancakes": {"0": {"quantity": "1.0 cups/batch"}}}, "Basic Pancakes": {"Pancakes": {"0": {"quantity": "1 batch/batch"}}}, "Baking Powder": {"Basic Pancakes": {"0": {"quantity": "2.0 teaspoons/batch"}}}, "Chicken Egg": {"Basic Pancakes": {"0": {"quantity": "1.0 egg/batch"}}}, "Unsalted Butter": {"Basic Pancakes": {"0": {"quantity": "2.0 tablespoons/batch"}}}, "Milk": {"Basic Pancakes": {"0": {"quantity": "1.0 cups/batch"}}}, "Table Salt": {"Basic Pancakes": {"0": {"quantity": "0.5 teaspoons/batch"}}}, "Granular White Sugar": {"Basic Pancakes": {"0": {"quantity": "2.0 tablespoons/batch"}}}, "Pancakes": {}, "Vegetable Oil": {"Basic Pancakes": {"0": {"quantity": "2.0 tablespoon / batch"}, "1": {"quantity": "1.0 tablespoon / batch"}}}}, "class": "TechGraph", "node": {"All-Purpose Flour": {}, "Basic Pancakes": {"parent groups": [["Unsalted Butter:0", "Vegetable Oil:1"], [null, "Maple Syrup:0"]]}, "Baking Powder": {}, "Chicken Egg": {}, "Unsalted Butter": {}, "Milk": {}, "Table Salt": {}, "Granular White Sugar": {}, "Pancakes": {}, "Vegetable Oil": {}}}